pyfsm/__init__.py
pyfsm/exceprions.py
pyfsm/machine.py
py_fsm-0.0.3.dist-info/METADATA
py_fsm-0.0.3.dist-info/WHEEL
py_fsm-0.0.3.dist-info/top_level.txt
py_fsm-0.0.3.dist-info/RECORD
